{"__symbolic":"module","version":4,"metadata":{"RATING_VALUE_ACCESSOR":{"provide":{"__symbolic":"reference","module":"@angular/forms","name":"NG_VALUE_ACCESSOR","line":5,"character":11},"useExisting":{"__symbolic":"reference","name":"Rating"},"multi":true},"Rating":{"__symbolic":"class","decorators":[{"__symbolic":"call","expression":{"__symbolic":"reference","module":"@angular/core","name":"Component","line":10,"character":1},"arguments":[{"selector":"p-rating","template":"\n        <div class=\"p-rating\" [ngClass]=\"{'p-readonly': readonly, 'p-disabled': disabled}\">\n            <span [attr.tabindex]=\"(disabled || readonly) ? null : '0'\" *ngIf=\"cancel\" (click)=\"clear($event)\" (keydown.enter)=\"clear($event)\" class=\"p-rating-icon p-rating-cancel\" [ngClass]=\"iconCancelClass\" [ngStyle]=\"iconCancelStyle\"></span>\n            <span *ngFor=\"let star of starsArray;let i=index\" class=\"p-rating-icon\" [attr.tabindex]=\"(disabled || readonly) ? null : '0'\"  (click)=\"rate($event,i)\" (keydown.enter)=\"rate($event,i)\"\n                [ngClass]=\"(!value || i >= value) ? iconOffClass : iconOnClass\"\n                [ngStyle]=\"(!value || i >= value) ? iconOffStyle : iconOnStyle\"></span>\n        </div>\n    ","providers":[{"__symbolic":"reference","name":"RATING_VALUE_ACCESSOR"}],"changeDetection":{"__symbolic":"select","expression":{"__symbolic":"reference","module":"@angular/core","name":"ChangeDetectionStrategy","line":21,"character":21},"member":"OnPush"},"encapsulation":{"__symbolic":"select","expression":{"__symbolic":"reference","module":"@angular/core","name":"ViewEncapsulation","line":22,"character":19},"member":"None"},"styles":[".p-rating-icon{cursor:pointer}.p-rating.p-rating-readonly .p-rating-icon{cursor:default}"]}]}],"members":{"disabled":[{"__symbolic":"property","decorators":[{"__symbolic":"call","expression":{"__symbolic":"reference","module":"@angular/core","name":"Input","line":27,"character":5}}]}],"readonly":[{"__symbolic":"property","decorators":[{"__symbolic":"call","expression":{"__symbolic":"reference","module":"@angular/core","name":"Input","line":29,"character":5}}]}],"stars":[{"__symbolic":"property","decorators":[{"__symbolic":"call","expression":{"__symbolic":"reference","module":"@angular/core","name":"Input","line":31,"character":5}}]}],"cancel":[{"__symbolic":"property","decorators":[{"__symbolic":"call","expression":{"__symbolic":"reference","module":"@angular/core","name":"Input","line":33,"character":5}}]}],"iconOnClass":[{"__symbolic":"property","decorators":[{"__symbolic":"call","expression":{"__symbolic":"reference","module":"@angular/core","name":"Input","line":35,"character":5}}]}],"iconOnStyle":[{"__symbolic":"property","decorators":[{"__symbolic":"call","expression":{"__symbolic":"reference","module":"@angular/core","name":"Input","line":37,"character":5}}]}],"iconOffClass":[{"__symbolic":"property","decorators":[{"__symbolic":"call","expression":{"__symbolic":"reference","module":"@angular/core","name":"Input","line":39,"character":5}}]}],"iconOffStyle":[{"__symbolic":"property","decorators":[{"__symbolic":"call","expression":{"__symbolic":"reference","module":"@angular/core","name":"Input","line":41,"character":5}}]}],"iconCancelClass":[{"__symbolic":"property","decorators":[{"__symbolic":"call","expression":{"__symbolic":"reference","module":"@angular/core","name":"Input","line":43,"character":5}}]}],"iconCancelStyle":[{"__symbolic":"property","decorators":[{"__symbolic":"call","expression":{"__symbolic":"reference","module":"@angular/core","name":"Input","line":45,"character":5}}]}],"onRate":[{"__symbolic":"property","decorators":[{"__symbolic":"call","expression":{"__symbolic":"reference","module":"@angular/core","name":"Output","line":47,"character":5}}]}],"onCancel":[{"__symbolic":"property","decorators":[{"__symbolic":"call","expression":{"__symbolic":"reference","module":"@angular/core","name":"Output","line":49,"character":5}}]}],"__ctor__":[{"__symbolic":"constructor","parameters":[{"__symbolic":"reference","module":"@angular/core","name":"ChangeDetectorRef","line":51,"character":28}]}],"ngOnInit":[{"__symbolic":"method"}],"rate":[{"__symbolic":"method"}],"clear":[{"__symbolic":"method"}],"writeValue":[{"__symbolic":"method"}],"registerOnChange":[{"__symbolic":"method"}],"registerOnTouched":[{"__symbolic":"method"}],"setDisabledState":[{"__symbolic":"method"}]}},"RatingModule":{"__symbolic":"class","decorators":[{"__symbolic":"call","expression":{"__symbolic":"reference","module":"@angular/core","name":"NgModule","line":110,"character":1},"arguments":[{"imports":[{"__symbolic":"reference","module":"@angular/common","name":"CommonModule","line":111,"character":14}],"exports":[{"__symbolic":"reference","name":"Rating"}],"declarations":[{"__symbolic":"reference","name":"Rating"}]}]}],"members":{}}},"origins":{"RATING_VALUE_ACCESSOR":"./rating","Rating":"./rating","RatingModule":"./rating"},"importAs":"primeng/rating"}